LICENSE
netlint/__init__.py
netlint/__main__.py
netlint/checks/__init__.py
netlint/checks/checker.py
netlint/checks/cisco_ios/__init__.py
netlint/checks/cisco_nxos/__init__.py
netlint/checks/constants.py
netlint/checks/utils.py
netlint/checks/various/__init__.py
netlint/cli/__init__.py
netlint/cli/main.py
netlint/cli/types.py
netlint/cli/utils.py
netlint-0.1.2.dist-info/entry_points.txt
netlint-0.1.2.dist-info/LICENSE
netlint-0.1.2.dist-info/WHEEL
netlint-0.1.2.dist-info/METADATA
netlint-0.1.2.dist-info/RECORD
