Metadata-Version: 2.1
Name: netlint
Version: 0.1.2
Summary: Performs static analysis on network device configuration files.
Home-page: https://netlint.readthedocs.io
License: GPLv3
Keywords: lint,networking
Author: Leo Kirchner
Author-email: leo@kirchne.red
Requires-Python: >=3.6.1,<4.0.0
Classifier: License :: Other/Proprietary License
Classifier: Operating System :: OS Independent
Classifier: Programming Language :: Python :: 3
Classifier: Programming Language :: Python :: 3.6
Classifier: Programming Language :: Python :: 3.7
Classifier: Programming Language :: Python :: 3.8
Classifier: Programming Language :: Python :: 3.9
Classifier: Topic :: Software Development :: Documentation
Classifier: Topic :: Software Development :: Quality Assurance
Provides-Extra: docs
Requires-Dist: ciscoconfparse (>=1.5.30,<2.0.0)
Requires-Dist: click (>=7.1.2,<8.0.0)
Requires-Dist: m2r2 (>=0.2.7,<0.3.0); extra == "docs"
Requires-Dist: sphinx (>=3.5.3,<4.0.0); extra == "docs"
Requires-Dist: sphinx-click (>=2.7.1,<3.0.0)
Requires-Dist: sphinx-rtd-theme (>=0.5.2,<0.6.0); extra == "docs"
Requires-Dist: toml (>=0.10.2,<0.11.0)
Requires-Dist: typing-extensions (>=3.7.4,<4.0.0)
Project-URL: Repository, https://github.com/Kircheneer/netlint
